{
    "DNDConfig": null,
    "_enabled_": false,
    "_margin_": [
        0,
        0,
        0,
        0
    ],
    "_orientation_": 1,
    "_padding_": [
        1,
        1,
        1,
        1
    ],
    "_percent_": true,
    "_position_": 2,
    "_resize_": true,
    "_skin_": "scfed8734cbe491a845f2b07b5f6efee",
    "allboxes": [],
    "android": {
        "@class": "com.kony.gen.viz.model.container.property.hbox.AndroidHBoxProperty",
        "_position_": 2,
        "position": 2,
        "render": true
    },
    "borderCollapse": false,
    "canUpdateUI": true,
    "children": [
        "btnNoMeeting"
    ],
    "containerweight": 100,
    "id": "hboxSection4",
    "info": null,
    "ipad": {
        "@class": "com.kony.gen.viz.model.container.property.hbox.IPadHBoxProperty",
        "_margin_": [
            0,
            20,
            0,
            118
        ],
        "_padding_": [
            420,
            0,
            0,
            0
        ],
        "_position_": 2,
        "margin": [
            0,
            20,
            0,
            118
        ],
        "marginInPixel": true,
        "padding": [
            420,
            0,
            0,
            0
        ],
        "paddingInPixel": true,
        "position": 2,
        "render": true
    },
    "isvisible": true,
    "kuid": "p2kwiet3578093092068",
    "layoutalignment": 3,
    "margininpixel": false,
    "name": "kony.ui.Box",
    "paddinginpixel": false,
    "parent": "frmSelectMeeting",
    "pf": "frmSelectMeeting",
    "spa": {
        "@class": "com.kony.gen.viz.model.container.property.hbox.SPAHBoxProperty"
    },
    "spaandroidtablet": {
        "@class": "com.kony.gen.viz.model.container.property.hbox.SPAAndroidTabletHBoxProperty",
        "render": true
    },
    "spaipad": {
        "@class": "com.kony.gen.viz.model.container.property.hbox.SPAIPadHBoxProperty",
        "render": true
    },
    "spawindowstablet": {
        "@class": "com.kony.gen.viz.model.container.property.hbox.SPAWindowsTabletHBoxProperty",
        "render": true
    },
    "templateType": "forms",
    "wType": "HBox",
    "widgetalignment": 5,
    "windows8": {
        "@class": "com.kony.gen.viz.model.container.property.hbox.Windows8HBoxProperty",
        "_margin_": [
            1,
            1,
            1,
            1
        ],
        "_position_": 2,
        "margin": [
            1,
            1,
            1,
            1
        ],
        "marginInPixel": true,
        "position": 2,
        "render": true
    }
}