{
    "DNDConfig": null,
    "_enabled_": false,
    "_margin_": [
        0,
        0,
        0,
        0
    ],
    "_padding_": [
        0,
        1,
        0,
        1
    ],
    "_skin_": "s0523f2594534c529e3496221334dcb0",
    "_text_": "",
    "android": {
        "@class": "com.kony.gen.viz.model.component.property.combobox.AndroidComboBoxProperty",
        "render": true
    },
    "canUpdateUI": true,
    "containerweight": 100,
    "contentalignment": 4,
    "hexpand": true,
    "id": "cmbApplyDiscount",
    "info": null,
    "ipad": {
        "@class": "com.kony.gen.viz.model.component.property.combobox.IPadComboBoxProperty",
        "psp": {
            "groupCells": false,
            "viewType": 3
        },
        "render": true
    },
    "isvisible": false,
    "kuid": "p2kwiet3578093093874",
    "margininpixel": false,
    "masterdata": [],
    "name": "kony.ui.ComboBox",
    "paddinginpixel": false,
    "parent": "popupDiscountData",
    "pf": "popupDiscountData",
    "selectedkey": "",
    "selectedkeyvalue": [],
    "spa": {
        "@class": "com.kony.gen.viz.model.component.property.combobox.SPAComboBoxProperty"
    },
    "spaandroidtablet": {
        "@class": "com.kony.gen.viz.model.component.property.combobox.SPAAndroidTabletComboBoxProperty",
        "render": true
    },
    "spaipad": {
        "@class": "com.kony.gen.viz.model.component.property.combobox.SPAIPadComboBoxProperty",
        "render": true
    },
    "spawindowstablet": {
        "@class": "com.kony.gen.viz.model.component.property.combobox.SPAWindowsTabletComboBoxProperty",
        "render": true
    },
    "vexpand": false,
    "wType": "ComboBox",
    "widgetalignment": 5,
    "windows8": {
        "@class": "com.kony.gen.viz.model.component.property.combobox.Windows8ComboBoxProperty",
        "_margin_": [
            1,
            1,
            1,
            1
        ],
        "margin": [
            1,
            1,
            1,
            1
        ],
        "marginInPixel": true,
        "render": true
    }
}