{
    "p2kwiet3578093091541_cmbStats_onSelection_seq0": {
        "id": "p2kwiet3578093091541_cmbStats_onSelection_seq0",
        "type": "ACTION_SEQUENCE",
        "params": [{
            "name": "eventobject",
            "value": "eventobject"
        }],
        "language": "js",
        "actions": [{
            "id": "customcode_onSelection_257443578093092316",
            "type": "INVOKE_FUNCTION",
            "sequenceKUID": "onclickStatisticsTabs",
            "display": "onclickStatisticsTabs",
            "inputparams": []
        }]
    }
}